geospark/__init__.py
geospark/exceptions.py
geospark/version.py
geospark/core/__init__.py
geospark/core/geom_types.py
geospark/core/utils.py
geospark/core/SpatialRDD/__init__.py
geospark/core/SpatialRDD/circle_rdd.py
geospark/core/SpatialRDD/linestring_rdd.py
geospark/core/SpatialRDD/point_rdd.py
geospark/core/SpatialRDD/polygon_rdd.py
geospark/core/SpatialRDD/rectangle_rdd.py
geospark/core/SpatialRDD/spatial_rdd.py
geospark/core/SpatialRDD/spatial_rdd_factory.py
geospark/core/enums/__init__.py
geospark/core/enums/file_data_splitter.py
geospark/core/enums/grid_type.py
geospark/core/enums/index_type.py
geospark/core/enums/join_build_side.py
geospark/core/enums/spatial.py
geospark/core/formatMapper/__init__.py
geospark/core/formatMapper/disc_utils.py
geospark/core/formatMapper/geo_json_reader.py
geospark/core/formatMapper/geo_reader.py
geospark/core/formatMapper/wkb_reader.py
geospark/core/formatMapper/wkt_reader.py
geospark/core/formatMapper/shapefileParser/__init__.py
geospark/core/formatMapper/shapefileParser/shape_file_reader.py
geospark/core/geom/__init__.py
geospark/core/geom/circle.py
geospark/core/geom/envelope.py
geospark/core/jvm/__init__.py
geospark/core/jvm/abstract.py
geospark/core/jvm/config.py
geospark/core/jvm/partitioner.py
geospark/core/spatialOperator/__init__.py
geospark/core/spatialOperator/join_params.py
geospark/core/spatialOperator/join_query.py
geospark/core/spatialOperator/knn_query.py
geospark/core/spatialOperator/range_query.py
geospark/jars/__init__.py
geospark/jars/2_2/__init__.py
geospark/jars/2_2/geo_wrapper_2.11-0.3.0.jar
geospark/jars/2_2/geospark-1.2.0.jar
geospark/jars/2_2/geospark-sql_2.2-1.2.0.jar
geospark/jars/2_3/__init__.py
geospark/jars/2_3/geo_wrapper_2.11-0.3.0.jar
geospark/jars/2_3/geospark-1.3.0.jar
geospark/jars/2_3/geospark-sql_2.3-1.3.0.jar
geospark/jars/2_4/__init__.py
geospark/jars/2_4/geo_wrapper_2.11-0.3.0.jar
geospark/jars/2_4/geospark-1.3.0.jar
geospark/jars/2_4/geospark-sql_2.3-1.3.0.jar
geospark-1.3.0.dist-info/LICENSE
geospark-1.3.0.dist-info/METADATA
geospark-1.3.0.dist-info/WHEEL
geospark-1.3.0.dist-info/top_level.txt
geospark-1.3.0.dist-info/RECORD
