Metadata-Version: 2.1
Name: geospark
Version: 1.3.0
Summary: GeoSpark Python
Home-page: https://github.com/DataSystemsLab/GeoSpark/tree/master/python
Author: Pawel Kocinski
Author-email: pawel93kocinski@gmail.com
License: UNKNOWN
Project-URL: Bug Reports, https://github.com/DataSystemsLab/GeoSpark
Platform: UNKNOWN
Classifier: Programming Language :: Python :: 3
Classifier: License :: OSI Approved :: Apache Software License
Requires-Python: >=3.6
Requires-Dist: pyspark
Requires-Dist: findspark
Requires-Dist: attrs
Requires-Dist: shapely
